emul_robot/__init__.py
emul_robot-0.1.0.dist-info/entry_points.txt
emul_robot-0.1.0.dist-info/WHEEL
emul_robot-0.1.0.dist-info/METADATA
emul_robot-0.1.0.dist-info/RECORD
