Metadata-Version: 2.1
Name: emul-robot
Version: 0.1.0
Summary: 
Author: Paul Choi
Author-email: straits9@gmail.com
Requires-Python: >=3.10,<4.0
Classifier: Programming Language :: Python :: 3
Classifier: Programming Language :: Python :: 3.10
Classifier: Programming Language :: Python :: 3.11
Requires-Dist: aio-pika (>=8.2.4,<9.0.0)
